{
  "fact_list": [
    {
      "fact_text": "Red traffic light means 'STOP'.",
      "source_citation": 0
    },
    {
      "fact_text": "Some junctions have an ALL RED period for safety or for pedestrians to cross.",
      "source_citation": 1
    },
    {
      "fact_text": "During an ALL RED period, all approaches show red signals simultaneously.",
      "source_citation": 2
    },
    {
      "fact_text": "Do not start to move until the green light appears.",
      "source_citation": 3
    },
    {
      "fact_text": "Amber traffic light means 'STOP' unless you are too close to the stop-line to stop safely.",
      "source_citation": 4
    },
    {
      "fact_text": "Flashing Amber traffic light means that traffic light signals are out of order.",
      "source_citation": 5
    },
    {
      "fact_text": "Flashing Amber signals indicate to proceed with caution and give way to traffic on the right.",
      "source_citation": 6
    },
    {
      "fact_text": "Green traffic light means 'GO'.",
      "source_citation": 8
    },
    {
      "fact_text": "Before proceeding on a Green light, look to the right and left to ensure it is safe.",
      "source_citation": 9
    },
    {
      "fact_text": "Green Arrow traffic light means 'GO' in the direction indicated after ensuring oncoming traffic is clear.",
      "source_citation": 10
    },
    {
      "fact_text": "Flickering Green Arrow means the signal is about to be cancelled.",
      "source_citation": 11
    },
    {
      "fact_text": "Do not proceed on a Flickering Green Arrow signal if you have not crossed the stop-line.",
      "source_citation": 12
    }
  ]
}
