{
  "fact_list": [
    {
      "fact_text": "A thin layer of water forms on the road surface on rainy days.",
      "source_citation": 0
    },
    {
      "fact_text": "Even good tyres may not have a good grip on the road.",
      "source_citation": 1
    },
    {
      "fact_text": "As speed increases, surface water builds up under the vehicle’s tyres.",
      "source_citation": 2
    },
    {
      "fact_text": "When surface water builds up under the tyres, the vehicle glides on the road surface, a phenomenon known as ‘Aquaplaning’.",
      "source_citation": 3
    },
    {
      "fact_text": "Aquaplaning results in the loss of steering control and braking efficiency.",
      "source_citation": 4
    },
    {
      "fact_text": "The faster the speed, the more difficult it is to control the vehicle.",
      "source_citation": 5
    },
    {
      "fact_text": "To counter aquaplaning, slow down by braking intermittently until control is regained.",
      "source_citation": 6
    },
    {
      "fact_text": "When approaching a road that is flooded but passable, engage a lower gear to traverse the flood.",
      "source_citation": 7
    },
    {
      "fact_text": "After passing through water, the brakes become ineffective.",
      "source_citation": 8
    },
    {
      "fact_text": "To dry ineffective brakes after passing through water, pump the brake pedal repeatedly until braking action returns.",
      "source_citation": 8
    },
    {
      "fact_text": "Brakes can also be dried by gently depressing the brake pedal with the left foot while pressing the accelerator with the right foot.",
      "source_citation": 9
    },
    {
      "fact_text": "At night, the depth of flood water can be deceptive.",
      "source_citation": 10
    },
    {
      "fact_text": "If uncertain about flood water depth, take an alternative route.",
      "source_citation": 11
    },
    {
      "fact_text": "Stretches of open highways are usually subjected to strong winds.",
      "source_citation": 12
    },
    {
      "fact_text": "To avoid being forced into the path of other traffic by strong winds, slow down and drive cautiously.",
      "source_citation": 13
    },
    {
      "fact_text": "Too much or too little light affects our ability to see.",
      "source_citation": 14
    },
    {
      "fact_text": "Sun-glare or light reflected off objects or pools of water on the road can dazzle and blind vision.",
      "source_citation": 15
    },
    {
      "fact_text": "To counter sun-glare, wear sunglasses or lower the sun-visor.",
      "source_citation": 16
    },
    {
      "fact_text": "Switch on your headlights from 7pm to 7am.",
      "source_citation": 17
    },
    {
      "fact_text": "Drive at a slower speed at night than during the day.",
      "source_citation": 18
    }
  ]
}
